{"@context": "http://www.shared-canvas.org/ns/context.json", "@id": "http://dl.cini.it/oa/collections/830/manifest.json", "@type": "sc:Manifest", "label": "L' infedelta' delusa dramma pastorale da rappresentarsi in musica nel Teatro delle Grazie in Vicenza in occasione della Fiera di maggio dell'anno 1729. Consagrato a S.S. E.E. il n.h. f. Antonio Diedo podesta', e vice capitanio, et la n.d. Andreana Michiel Diedo sua degnissima consorte", "sequences": [{"@id": "http://dl.cini.it/oa/collections/830/sequence.json", "@type": "sc:Sequence", "label": "", "canvases": [{"@id": "http://dl.cini.it/oa/items/26510/canvas.json", "label": "coperta_1", "@type": "sc:Canvas", "width": 2220, "height": 3723, "images": [{"@id": "http://dl.cini.it/oa/files/26510/anno.json", "motivation": "sc:painting", "@type": "oa:Annotation", "resource": {"@id": "http://dl.cini.it/files/original/7098225a08ea6a1ccfcf9bb71067b431.jpg", "@type": "dctypes:Image", "format": "image/jpeg", "width": 2220, "height": 3723, "service": {"@id": "http://dl.cini.it:8080/digilib/Scaler/IIIF/7098225a08ea6a1ccfcf9bb71067b431.jpg", "@context": "http://iiif.io/api/image/2/context.json", "profile": "http://iiif.io/api/image/2/level2.json"}}, "on": "http://dl.cini.it/oa/items/26510/canvas.json"}], "metadata": [{"label": "Identifier", "value": "74075b1f-09c8-4e91-a425-3261080f66cf"}, {"label": "originalFileName", "value": "234855_ROL.0776.06.01.tif"}, {"label": "cartulazione1", "value": "coperta_1"}, {"label": "exifData", "value": "ColorSpace=-1;NativeDigest=36864,40960,40961,37121,37122,40962,40963,37510,40964,36867,36868,33434,33437,34850,34852,34855,34856,37377,37378,37379,37380,37381,37382,37383,37384,37385,37386,37396,41483,41484,41486,41487,41488,41492,41493,41495,41728,41729,41730,41985,41986,41987,41988,41989,41990,41991,41992,41993,41994,41995,41996,42016,0,2,4,5,6,7,8,9,10,11,12,13,14,15,16,17,18,20,22,23,24,25,26,27,28,30;8F90EBD7A2579E55BCCA6A1AE7443648;PixelXDimension=2220;PixelYDimension=3723"}, {"label": "filename", "value": "1.jpg"}, {"label": "fileMD5", "value": "5e75c30bdc83c58e8ec6bf3dfa15200f"}], "otherContent": [{"@id": "http://dl.cini.it/oa/items/26510/annolist.json", "@type": "sc:AnnotationList"}]}, {"@id": "http://dl.cini.it/oa/items/26511/canvas.json", "label": "coperta_2, p. [1]", "@type": "sc:Canvas", "width": 4180, "height": 3714, "images": [{"@id": "http://dl.cini.it/oa/files/26511/anno.json", "motivation": "sc:painting", "@type": "oa:Annotation", "resource": {"@id": "http://dl.cini.it/files/original/0159c50f6a44e29bd261471960b0958d.jpg", "@type": "dctypes:Image", "format": "image/jpeg", "width": 4180, "height": 3714, "service": {"@id": "http://dl.cini.it:8080/digilib/Scaler/IIIF/0159c50f6a44e29bd261471960b0958d.jpg", "@context": "http://iiif.io/api/image/2/context.json", "profile": "http://iiif.io/api/image/2/level2.json"}}, "on": "http://dl.cini.it/oa/items/26511/canvas.json"}], "metadata": [{"label": "Identifier", "value": "12fdbce3-832c-461d-a05b-730f55209e1b"}, {"label": "originalFileName", "value": "234857_ROL.0776.06.02.tif"}, {"label": "cartulazione1", "value": "coperta_2, p. [1]"}, {"label": "exifData", "value": "ColorSpace=-1;NativeDigest=36864,40960,40961,37121,37122,40962,40963,37510,40964,36867,36868,33434,33437,34850,34852,34855,34856,37377,37378,37379,37380,37381,37382,37383,37384,37385,37386,37396,41483,41484,41486,41487,41488,41492,41493,41495,41728,41729,41730,41985,41986,41987,41988,41989,41990,41991,41992,41993,41994,41995,41996,42016,0,2,4,5,6,7,8,9,10,11,12,13,14,15,16,17,18,20,22,23,24,25,26,27,28,30;738D6BAC6BCA8A9EB7E3B695F1D20AFD;PixelXDimension=4180;PixelYDimension=3714"}, {"label": "filename", "value": "2.jpg"}, {"label": "fileMD5", "value": "4713f5ada255843061c66dfdfc0acec8"}], "otherContent": [{"@id": "http://dl.cini.it/oa/items/26511/annolist.json", "@type": "sc:AnnotationList"}]}, {"@id": "http://dl.cini.it/oa/items/26512/canvas.json", "label": "p. [2], p. [3] (frontespizio)", "@type": "sc:Canvas", "width": 4180, "height": 3714, "images": [{"@id": "http://dl.cini.it/oa/files/26512/anno.json", "motivation": "sc:painting", "@type": "oa:Annotation", "resource": {"@id": "http://dl.cini.it/files/original/82c8882fabd048b9835dcf310d1ac6d5.jpg", "@type": "dctypes:Image", "format": "image/jpeg", "width": 4180, "height": 3714, "service": {"@id": "http://dl.cini.it:8080/digilib/Scaler/IIIF/82c8882fabd048b9835dcf310d1ac6d5.jpg", "@context": "http://iiif.io/api/image/2/context.json", "profile": "http://iiif.io/api/image/2/level2.json"}}, "on": "http://dl.cini.it/oa/items/26512/canvas.json"}], "metadata": [{"label": "Identifier", "value": "769841af-755b-4ac9-8760-4e14b5cecd4e"}, {"label": "originalFileName", "value": "234859_ROL.0776.06.03.tif"}, {"label": "cartulazione1", "value": "p. [2], p. [3] (frontespizio)"}, {"label": "exifData", "value": "ColorSpace=-1;NativeDigest=36864,40960,40961,37121,37122,40962,40963,37510,40964,36867,36868,33434,33437,34850,34852,34855,34856,37377,37378,37379,37380,37381,37382,37383,37384,37385,37386,37396,41483,41484,41486,41487,41488,41492,41493,41495,41728,41729,41730,41985,41986,41987,41988,41989,41990,41991,41992,41993,41994,41995,41996,42016,0,2,4,5,6,7,8,9,10,11,12,13,14,15,16,17,18,20,22,23,24,25,26,27,28,30;738D6BAC6BCA8A9EB7E3B695F1D20AFD;PixelXDimension=4180;PixelYDimension=3714"}, {"label": "filename", "value": "3.jpg"}, {"label": "fileMD5", "value": "f6e60d5786d7ae9caea3b20690c752dd"}], "otherContent": [{"@id": "http://dl.cini.it/oa/items/26512/annolist.json", "@type": "sc:AnnotationList"}]}, {"@id": "http://dl.cini.it/oa/items/26513/canvas.json", "label": "p. [4], p. [5]", "@type": "sc:Canvas", "width": 4216, "height": 3723, "images": [{"@id": "http://dl.cini.it/oa/files/26513/anno.json", "motivation": "sc:painting", "@type": "oa:Annotation", "resource": {"@id": "http://dl.cini.it/files/original/12eacb83fe6d2fe3f6c491d9bf482409.jpg", "@type": "dctypes:Image", "format": "image/jpeg", "width": 4216, "height": 3723, "service": {"@id": "http://dl.cini.it:8080/digilib/Scaler/IIIF/12eacb83fe6d2fe3f6c491d9bf482409.jpg", "@context": "http://iiif.io/api/image/2/context.json", "profile": "http://iiif.io/api/image/2/level2.json"}}, "on": "http://dl.cini.it/oa/items/26513/canvas.json"}], "metadata": [{"label": "Identifier", "value": "5d95594d-970e-4500-aaa7-f452fd58c0c1"}, {"label": "originalFileName", "value": "234861_ROL.0776.06.04.tif"}, {"label": "cartulazione1", "value": "p. [4], p. [5]"}, {"label": "exifData", "value": "ColorSpace=-1;NativeDigest=36864,40960,40961,37121,37122,40962,40963,37510,40964,36867,36868,33434,33437,34850,34852,34855,34856,37377,37378,37379,37380,37381,37382,37383,37384,37385,37386,37396,41483,41484,41486,41487,41488,41492,41493,41495,41728,41729,41730,41985,41986,41987,41988,41989,41990,41991,41992,41993,41994,41995,41996,42016,0,2,4,5,6,7,8,9,10,11,12,13,14,15,16,17,18,20,22,23,24,25,26,27,28,30;83797D6D0CDCA6E8F7E0BD53DF705C35;PixelXDimension=4216;PixelYDimension=3723"}, {"label": "filename", "value": "4.jpg"}, {"label": "fileMD5", "value": "37c5e96e45d1a19fd8c9d94d94c04d01"}], "otherContent": [{"@id": "http://dl.cini.it/oa/items/26513/annolist.json", "@type": "sc:AnnotationList"}]}, {"@id": "http://dl.cini.it/oa/items/26514/canvas.json", "label": "p. [6], p. 7", "@type": "sc:Canvas", "width": 4216, "height": 3723, "images": [{"@id": "http://dl.cini.it/oa/files/26514/anno.json", "motivation": "sc:painting", "@type": "oa:Annotation", "resource": {"@id": "http://dl.cini.it/files/original/fa378e68a2416bc6c1f29fd8fa0e4acc.jpg", "@type": "dctypes:Image", "format": "image/jpeg", "width": 4216, "height": 3723, "service": {"@id": "http://dl.cini.it:8080/digilib/Scaler/IIIF/fa378e68a2416bc6c1f29fd8fa0e4acc.jpg", "@context": "http://iiif.io/api/image/2/context.json", "profile": "http://iiif.io/api/image/2/level2.json"}}, "on": "http://dl.cini.it/oa/items/26514/canvas.json"}], "metadata": [{"label": "Identifier", "value": "e8a0877c-5434-4340-bd1c-11c5c767bbbd"}, {"label": "originalFileName", "value": "234863_ROL.0776.06.05.tif"}, {"label": "cartulazione1", "value": "p. [6], p. 7"}, {"label": "exifData", "value": "ColorSpace=-1;NativeDigest=36864,40960,40961,37121,37122,40962,40963,37510,40964,36867,36868,33434,33437,34850,34852,34855,34856,37377,37378,37379,37380,37381,37382,37383,37384,37385,37386,37396,41483,41484,41486,41487,41488,41492,41493,41495,41728,41729,41730,41985,41986,41987,41988,41989,41990,41991,41992,41993,41994,41995,41996,42016,0,2,4,5,6,7,8,9,10,11,12,13,14,15,16,17,18,20,22,23,24,25,26,27,28,30;83797D6D0CDCA6E8F7E0BD53DF705C35;PixelXDimension=4216;PixelYDimension=3723"}, {"label": "filename", "value": "5.jpg"}, {"label": "fileMD5", "value": "57cee19f5eea8c4f96ebb467481fc8c5"}], "otherContent": [{"@id": "http://dl.cini.it/oa/items/26514/annolist.json", "@type": "sc:AnnotationList"}]}, {"@id": "http://dl.cini.it/oa/items/26515/canvas.json", "label": "p. 8, p. 9", "@type": "sc:Canvas", "width": 4188, "height": 3723, "images": [{"@id": "http://dl.cini.it/oa/files/26515/anno.json", "motivation": "sc:painting", "@type": "oa:Annotation", "resource": {"@id": "http://dl.cini.it/files/original/820aaa754791bbc670ded928df7d4747.jpg", "@type": "dctypes:Image", "format": "image/jpeg", "width": 4188, "height": 3723, "service": {"@id": "http://dl.cini.it:8080/digilib/Scaler/IIIF/820aaa754791bbc670ded928df7d4747.jpg", "@context": "http://iiif.io/api/image/2/context.json", "profile": "http://iiif.io/api/image/2/level2.json"}}, "on": "http://dl.cini.it/oa/items/26515/canvas.json"}], "metadata": [{"label": "Identifier", "value": "1bc13c1e-a366-4917-90ca-daaad21e662d"}, {"label": "originalFileName", "value": "234865_ROL.0776.06.06.tif"}, {"label": "cartulazione1", "value": "p. 8, p. 9"}, {"label": "exifData", "value": "ColorSpace=-1;NativeDigest=36864,40960,40961,37121,37122,40962,40963,37510,40964,36867,36868,33434,33437,34850,34852,34855,34856,37377,37378,37379,37380,37381,37382,37383,37384,37385,37386,37396,41483,41484,41486,41487,41488,41492,41493,41495,41728,41729,41730,41985,41986,41987,41988,41989,41990,41991,41992,41993,41994,41995,41996,42016,0,2,4,5,6,7,8,9,10,11,12,13,14,15,16,17,18,20,22,23,24,25,26,27,28,30;A4D13B3827C9F72C8B87F02658F3FB17;PixelXDimension=4188;PixelYDimension=3723"}, {"label": "filename", "value": "6.jpg"}, {"label": "fileMD5", "value": "84db18dbcce42eec12c219caa6b088aa"}], "otherContent": [{"@id": "http://dl.cini.it/oa/items/26515/annolist.json", "@type": "sc:AnnotationList"}]}, {"@id": "http://dl.cini.it/oa/items/26516/canvas.json", "label": "p. 10, p. 11", "@type": "sc:Canvas", "width": 4162, "height": 3723, "images": [{"@id": "http://dl.cini.it/oa/files/26516/anno.json", "motivation": "sc:painting", "@type": "oa:Annotation", "resource": {"@id": "http://dl.cini.it/files/original/0385e1ac1a9b895fbc7aac75ea681da5.jpg", "@type": "dctypes:Image", "format": "image/jpeg", "width": 4162, "height": 3723, "service": {"@id": "http://dl.cini.it:8080/digilib/Scaler/IIIF/0385e1ac1a9b895fbc7aac75ea681da5.jpg", "@context": "http://iiif.io/api/image/2/context.json", "profile": "http://iiif.io/api/image/2/level2.json"}}, "on": "http://dl.cini.it/oa/items/26516/canvas.json"}], "metadata": [{"label": "Identifier", "value": "0afe1b89-ca16-4f38-96ad-026f25a5c0c3"}, {"label": "originalFileName", "value": "234867_ROL.0776.06.07.tif"}, {"label": "cartulazione1", "value": "p. 10, p. 11"}, {"label": "exifData", "value": "ColorSpace=-1;NativeDigest=36864,40960,40961,37121,37122,40962,40963,37510,40964,36867,36868,33434,33437,34850,34852,34855,34856,37377,37378,37379,37380,37381,37382,37383,37384,37385,37386,37396,41483,41484,41486,41487,41488,41492,41493,41495,41728,41729,41730,41985,41986,41987,41988,41989,41990,41991,41992,41993,41994,41995,41996,42016,0,2,4,5,6,7,8,9,10,11,12,13,14,15,16,17,18,20,22,23,24,25,26,27,28,30;D91764B97AECACA8A8386BB23B18ACD7;PixelXDimension=4162;PixelYDimension=3723"}, {"label": "filename", "value": "7.jpg"}, {"label": "fileMD5", "value": "4c9aeed32f33e29ad2ed6bc0ae015bb0"}], "otherContent": [{"@id": "http://dl.cini.it/oa/items/26516/annolist.json", "@type": "sc:AnnotationList"}]}, {"@id": "http://dl.cini.it/oa/items/26517/canvas.json", "label": "p. 12, p. 13", "@type": "sc:Canvas", "width": 4162, "height": 3723, "images": [{"@id": "http://dl.cini.it/oa/files/26517/anno.json", "motivation": "sc:painting", "@type": "oa:Annotation", "resource": {"@id": "http://dl.cini.it/files/original/5954e8c73d6609f6e8e4939353d3deff.jpg", "@type": "dctypes:Image", "format": "image/jpeg", "width": 4162, "height": 3723, "service": {"@id": "http://dl.cini.it:8080/digilib/Scaler/IIIF/5954e8c73d6609f6e8e4939353d3deff.jpg", "@context": "http://iiif.io/api/image/2/context.json", "profile": "http://iiif.io/api/image/2/level2.json"}}, "on": "http://dl.cini.it/oa/items/26517/canvas.json"}], "metadata": [{"label": "Identifier", "value": "7240c68d-7955-442b-99e8-11efa1e5fbee"}, {"label": "originalFileName", "value": "234869_ROL.0776.06.08.tif"}, {"label": "cartulazione1", "value": "p. 12, p. 13"}, {"label": "exifData", "value": "ColorSpace=-1;NativeDigest=36864,40960,40961,37121,37122,40962,40963,37510,40964,36867,36868,33434,33437,34850,34852,34855,34856,37377,37378,37379,37380,37381,37382,37383,37384,37385,37386,37396,41483,41484,41486,41487,41488,41492,41493,41495,41728,41729,41730,41985,41986,41987,41988,41989,41990,41991,41992,41993,41994,41995,41996,42016,0,2,4,5,6,7,8,9,10,11,12,13,14,15,16,17,18,20,22,23,24,25,26,27,28,30;D91764B97AECACA8A8386BB23B18ACD7;PixelXDimension=4162;PixelYDimension=3723"}, {"label": "filename", "value": "8.jpg"}, {"label": "fileMD5", "value": "c251dccad19d2b6562b60fe11874a1eb"}], "otherContent": [{"@id": "http://dl.cini.it/oa/items/26517/annolist.json", "@type": "sc:AnnotationList"}]}, {"@id": "http://dl.cini.it/oa/items/26518/canvas.json", "label": "p. 14, p. 15", "@type": "sc:Canvas", "width": 4162, "height": 3723, "images": [{"@id": "http://dl.cini.it/oa/files/26518/anno.json", "motivation": "sc:painting", "@type": "oa:Annotation", "resource": {"@id": "http://dl.cini.it/files/original/9cbd96b1ca5211c2dd028694806906c3.jpg", "@type": "dctypes:Image", "format": "image/jpeg", "width": 4162, "height": 3723, "service": {"@id": "http://dl.cini.it:8080/digilib/Scaler/IIIF/9cbd96b1ca5211c2dd028694806906c3.jpg", "@context": "http://iiif.io/api/image/2/context.json", "profile": "http://iiif.io/api/image/2/level2.json"}}, "on": "http://dl.cini.it/oa/items/26518/canvas.json"}], "metadata": [{"label": "Identifier", "value": "a50c344d-0488-471c-9593-881f4837b2e5"}, {"label": "originalFileName", "value": "234871_ROL.0776.06.09.tif"}, {"label": "cartulazione1", "value": "p. 14, p. 15"}, {"label": "exifData", "value": "ColorSpace=-1;NativeDigest=36864,40960,40961,37121,37122,40962,40963,37510,40964,36867,36868,33434,33437,34850,34852,34855,34856,37377,37378,37379,37380,37381,37382,37383,37384,37385,37386,37396,41483,41484,41486,41487,41488,41492,41493,41495,41728,41729,41730,41985,41986,41987,41988,41989,41990,41991,41992,41993,41994,41995,41996,42016,0,2,4,5,6,7,8,9,10,11,12,13,14,15,16,17,18,20,22,23,24,25,26,27,28,30;D91764B97AECACA8A8386BB23B18ACD7;PixelXDimension=4162;PixelYDimension=3723"}, {"label": "filename", "value": "9.jpg"}, {"label": "fileMD5", "value": "183d404dabefc2f4aeb24d0a73bbac94"}], "otherContent": [{"@id": "http://dl.cini.it/oa/items/26518/annolist.json", "@type": "sc:AnnotationList"}]}, {"@id": "http://dl.cini.it/oa/items/26519/canvas.json", "label": "p. 16, p. 17", "@type": "sc:Canvas", "width": 4144, "height": 3723, "images": [{"@id": "http://dl.cini.it/oa/files/26519/anno.json", "motivation": "sc:painting", "@type": "oa:Annotation", "resource": {"@id": "http://dl.cini.it/files/original/1176aed2e7e7ed1cbe28a60df2dec3d2.jpg", "@type": "dctypes:Image", "format": "image/jpeg", "width": 4144, "height": 3723, "service": {"@id": "http://dl.cini.it:8080/digilib/Scaler/IIIF/1176aed2e7e7ed1cbe28a60df2dec3d2.jpg", "@context": "http://iiif.io/api/image/2/context.json", "profile": "http://iiif.io/api/image/2/level2.json"}}, "on": "http://dl.cini.it/oa/items/26519/canvas.json"}], "metadata": [{"label": "Identifier", "value": "603912f3-0abb-42ec-ad16-fa1f4162ffd7"}, {"label": "originalFileName", "value": "234873_ROL.0776.06.10.tif"}, {"label": "cartulazione1", "value": "p. 16, p. 17"}, {"label": "exifData", "value": "ColorSpace=-1;NativeDigest=36864,40960,40961,37121,37122,40962,40963,37510,40964,36867,36868,33434,33437,34850,34852,34855,34856,37377,37378,37379,37380,37381,37382,37383,37384,37385,37386,37396,41483,41484,41486,41487,41488,41492,41493,41495,41728,41729,41730,41985,41986,41987,41988,41989,41990,41991,41992,41993,41994,41995,41996,42016,0,2,4,5,6,7,8,9,10,11,12,13,14,15,16,17,18,20,22,23,24,25,26,27,28,30;4840B13F7902FDA90B07872A94506285;PixelXDimension=4144;PixelYDimension=3723"}, {"label": "filename", "value": "10.jpg"}, {"label": "fileMD5", "value": "235c44de8a0bd885af04de358f8d26af"}], "otherContent": [{"@id": "http://dl.cini.it/oa/items/26519/annolist.json", "@type": "sc:AnnotationList"}]}, {"@id": "http://dl.cini.it/oa/items/26520/canvas.json", "label": "p. 18, p. 19", "@type": "sc:Canvas", "width": 4170, "height": 3723, "images": [{"@id": "http://dl.cini.it/oa/files/26520/anno.json", "motivation": "sc:painting", "@type": "oa:Annotation", "resource": {"@id": "http://dl.cini.it/files/original/82991e9080f52ac9265da20e2a48bc65.jpg", "@type": "dctypes:Image", "format": "image/jpeg", "width": 4170, "height": 3723, "service": {"@id": "http://dl.cini.it:8080/digilib/Scaler/IIIF/82991e9080f52ac9265da20e2a48bc65.jpg", "@context": "http://iiif.io/api/image/2/context.json", "profile": "http://iiif.io/api/image/2/level2.json"}}, "on": "http://dl.cini.it/oa/items/26520/canvas.json"}], "metadata": [{"label": "Identifier", "value": "55c0842f-a449-4f8c-9619-5ca036a1a58a"}, {"label": "originalFileName", "value": "234875_ROL.0776.06.11.tif"}, {"label": "cartulazione1", "value": "p. 18, p. 19"}, {"label": "exifData", "value": "ColorSpace=-1;NativeDigest=36864,40960,40961,37121,37122,40962,40963,37510,40964,36867,36868,33434,33437,34850,34852,34855,34856,37377,37378,37379,37380,37381,37382,37383,37384,37385,37386,37396,41483,41484,41486,41487,41488,41492,41493,41495,41728,41729,41730,41985,41986,41987,41988,41989,41990,41991,41992,41993,41994,41995,41996,42016,0,2,4,5,6,7,8,9,10,11,12,13,14,15,16,17,18,20,22,23,24,25,26,27,28,30;3A27FEBDCF1DC040E25E9CBD9489C3B3;PixelXDimension=4170;PixelYDimension=3723"}, {"label": "filename", "value": "11.jpg"}, {"label": "fileMD5", "value": "cf66644cfa6af573f50b0f4e48ea6a6b"}], "otherContent": [{"@id": "http://dl.cini.it/oa/items/26520/annolist.json", "@type": "sc:AnnotationList"}]}, {"@id": "http://dl.cini.it/oa/items/26521/canvas.json", "label": "p. 20, p. 21", "@type": "sc:Canvas", "width": 4170, "height": 3723, "images": [{"@id": "http://dl.cini.it/oa/files/26521/anno.json", "motivation": "sc:painting", "@type": "oa:Annotation", "resource": {"@id": "http://dl.cini.it/files/original/993c343e78ebcfbd17d4e3942905a477.jpg", "@type": "dctypes:Image", "format": "image/jpeg", "width": 4170, "height": 3723, "service": {"@id": "http://dl.cini.it:8080/digilib/Scaler/IIIF/993c343e78ebcfbd17d4e3942905a477.jpg", "@context": "http://iiif.io/api/image/2/context.json", "profile": "http://iiif.io/api/image/2/level2.json"}}, "on": "http://dl.cini.it/oa/items/26521/canvas.json"}], "metadata": [{"label": "Identifier", "value": "246aee38-f51b-428c-b663-bde90bd2dc12"}, {"label": "originalFileName", "value": "234877_ROL.0776.06.12.tif"}, {"label": "cartulazione1", "value": "p. 20, p. 21"}, {"label": "exifData", "value": "ColorSpace=-1;NativeDigest=36864,40960,40961,37121,37122,40962,40963,37510,40964,36867,36868,33434,33437,34850,34852,34855,34856,37377,37378,37379,37380,37381,37382,37383,37384,37385,37386,37396,41483,41484,41486,41487,41488,41492,41493,41495,41728,41729,41730,41985,41986,41987,41988,41989,41990,41991,41992,41993,41994,41995,41996,42016,0,2,4,5,6,7,8,9,10,11,12,13,14,15,16,17,18,20,22,23,24,25,26,27,28,30;3A27FEBDCF1DC040E25E9CBD9489C3B3;PixelXDimension=4170;PixelYDimension=3723"}, {"label": "filename", "value": "12.jpg"}, {"label": "fileMD5", "value": "4f423031c8a633fe8f5211cefb176c7d"}], "otherContent": [{"@id": "http://dl.cini.it/oa/items/26521/annolist.json", "@type": "sc:AnnotationList"}]}, {"@id": "http://dl.cini.it/oa/items/26522/canvas.json", "label": "p. 22, p. 23", "@type": "sc:Canvas", "width": 4170, "height": 3723, "images": [{"@id": "http://dl.cini.it/oa/files/26522/anno.json", "motivation": "sc:painting", "@type": "oa:Annotation", "resource": {"@id": "http://dl.cini.it/files/original/c46c947426febbdd7f5522768904445c.jpg", "@type": "dctypes:Image", "format": "image/jpeg", "width": 4170, "height": 3723, "service": {"@id": "http://dl.cini.it:8080/digilib/Scaler/IIIF/c46c947426febbdd7f5522768904445c.jpg", "@context": "http://iiif.io/api/image/2/context.json", "profile": "http://iiif.io/api/image/2/level2.json"}}, "on": "http://dl.cini.it/oa/items/26522/canvas.json"}], "metadata": [{"label": "Identifier", "value": "d3d2fde8-a18f-4d7a-8f48-62e378cf05fb"}, {"label": "originalFileName", "value": "234879_ROL.0776.06.13.tif"}, {"label": "cartulazione1", "value": "p. 22, p. 23"}, {"label": "exifData", "value": "ColorSpace=-1;NativeDigest=36864,40960,40961,37121,37122,40962,40963,37510,40964,36867,36868,33434,33437,34850,34852,34855,34856,37377,37378,37379,37380,37381,37382,37383,37384,37385,37386,37396,41483,41484,41486,41487,41488,41492,41493,41495,41728,41729,41730,41985,41986,41987,41988,41989,41990,41991,41992,41993,41994,41995,41996,42016,0,2,4,5,6,7,8,9,10,11,12,13,14,15,16,17,18,20,22,23,24,25,26,27,28,30;3A27FEBDCF1DC040E25E9CBD9489C3B3;PixelXDimension=4170;PixelYDimension=3723"}, {"label": "filename", "value": "13.jpg"}, {"label": "fileMD5", "value": "72d5f13b17fb56c37d329e32427881c3"}], "otherContent": [{"@id": "http://dl.cini.it/oa/items/26522/annolist.json", "@type": "sc:AnnotationList"}]}, {"@id": "http://dl.cini.it/oa/items/26523/canvas.json", "label": "p. 24, p. 25", "@type": "sc:Canvas", "width": 4180, "height": 3723, "images": [{"@id": "http://dl.cini.it/oa/files/26523/anno.json", "motivation": "sc:painting", "@type": "oa:Annotation", "resource": {"@id": "http://dl.cini.it/files/original/b9dad15fa683130b30776b9ae21826a6.jpg", "@type": "dctypes:Image", "format": "image/jpeg", "width": 4180, "height": 3723, "service": {"@id": "http://dl.cini.it:8080/digilib/Scaler/IIIF/b9dad15fa683130b30776b9ae21826a6.jpg", "@context": "http://iiif.io/api/image/2/context.json", "profile": "http://iiif.io/api/image/2/level2.json"}}, "on": "http://dl.cini.it/oa/items/26523/canvas.json"}], "metadata": [{"label": "Identifier", "value": "798ac461-49a5-4341-98b6-80221a33723c"}, {"label": "originalFileName", "value": "234881_ROL.0776.06.14.tif"}, {"label": "cartulazione1", "value": "p. 24, p. 25"}, {"label": "exifData", "value": "ColorSpace=-1;NativeDigest=36864,40960,40961,37121,37122,40962,40963,37510,40964,36867,36868,33434,33437,34850,34852,34855,34856,37377,37378,37379,37380,37381,37382,37383,37384,37385,37386,37396,41483,41484,41486,41487,41488,41492,41493,41495,41728,41729,41730,41985,41986,41987,41988,41989,41990,41991,41992,41993,41994,41995,41996,42016,0,2,4,5,6,7,8,9,10,11,12,13,14,15,16,17,18,20,22,23,24,25,26,27,28,30;D9D35E60029BE1FFA87BE12FF71ECBFD;PixelXDimension=4180;PixelYDimension=3723"}, {"label": "filename", "value": "14.jpg"}, {"label": "fileMD5", "value": "9de9e218cc5474a6b8010054fa4400ec"}], "otherContent": [{"@id": "http://dl.cini.it/oa/items/26523/annolist.json", "@type": "sc:AnnotationList"}]}, {"@id": "http://dl.cini.it/oa/items/26524/canvas.json", "label": "p. 26, p. 27", "@type": "sc:Canvas", "width": 4170, "height": 3723, "images": [{"@id": "http://dl.cini.it/oa/files/26524/anno.json", "motivation": "sc:painting", "@type": "oa:Annotation", "resource": {"@id": "http://dl.cini.it/files/original/8464bea0e7fd4d101a767eade92609d7.jpg", "@type": "dctypes:Image", "format": "image/jpeg", "width": 4170, "height": 3723, "service": {"@id": "http://dl.cini.it:8080/digilib/Scaler/IIIF/8464bea0e7fd4d101a767eade92609d7.jpg", "@context": "http://iiif.io/api/image/2/context.json", "profile": "http://iiif.io/api/image/2/level2.json"}}, "on": "http://dl.cini.it/oa/items/26524/canvas.json"}], "metadata": [{"label": "Identifier", "value": "8df36168-8fc2-416c-855c-852e21eb7445"}, {"label": "originalFileName", "value": "234883_ROL.0776.06.15.tif"}, {"label": "cartulazione1", "value": "p. 26, p. 27"}, {"label": "exifData", "value": "ColorSpace=-1;NativeDigest=36864,40960,40961,37121,37122,40962,40963,37510,40964,36867,36868,33434,33437,34850,34852,34855,34856,37377,37378,37379,37380,37381,37382,37383,37384,37385,37386,37396,41483,41484,41486,41487,41488,41492,41493,41495,41728,41729,41730,41985,41986,41987,41988,41989,41990,41991,41992,41993,41994,41995,41996,42016,0,2,4,5,6,7,8,9,10,11,12,13,14,15,16,17,18,20,22,23,24,25,26,27,28,30;3A27FEBDCF1DC040E25E9CBD9489C3B3;PixelXDimension=4170;PixelYDimension=3723"}, {"label": "filename", "value": "15.jpg"}, {"label": "fileMD5", "value": "d81318a86ba0e09c9dff03d22796efc1"}], "otherContent": [{"@id": "http://dl.cini.it/oa/items/26524/annolist.json", "@type": "sc:AnnotationList"}]}, {"@id": "http://dl.cini.it/oa/items/26525/canvas.json", "label": "p. 28, p. 29", "@type": "sc:Canvas", "width": 4152, "height": 3723, "images": [{"@id": "http://dl.cini.it/oa/files/26525/anno.json", "motivation": "sc:painting", "@type": "oa:Annotation", "resource": {"@id": "http://dl.cini.it/files/original/4bdd72080122e5244ee65c7f390a33ce.jpg", "@type": "dctypes:Image", "format": "image/jpeg", "width": 4152, "height": 3723, "service": {"@id": "http://dl.cini.it:8080/digilib/Scaler/IIIF/4bdd72080122e5244ee65c7f390a33ce.jpg", "@context": "http://iiif.io/api/image/2/context.json", "profile": "http://iiif.io/api/image/2/level2.json"}}, "on": "http://dl.cini.it/oa/items/26525/canvas.json"}], "metadata": [{"label": "Identifier", "value": "c20fbaa5-01a2-4ba3-9803-8e3fc3dc9e2f"}, {"label": "originalFileName", "value": "234885_ROL.0776.06.16.tif"}, {"label": "cartulazione1", "value": "p. 28, p. 29"}, {"label": "exifData", "value": "ColorSpace=-1;NativeDigest=36864,40960,40961,37121,37122,40962,40963,37510,40964,36867,36868,33434,33437,34850,34852,34855,34856,37377,37378,37379,37380,37381,37382,37383,37384,37385,37386,37396,41483,41484,41486,41487,41488,41492,41493,41495,41728,41729,41730,41985,41986,41987,41988,41989,41990,41991,41992,41993,41994,41995,41996,42016,0,2,4,5,6,7,8,9,10,11,12,13,14,15,16,17,18,20,22,23,24,25,26,27,28,30;853D799F9572868E5B98F867195DD545;PixelXDimension=4152;PixelYDimension=3723"}, {"label": "filename", "value": "16.jpg"}, {"label": "fileMD5", "value": "93834f7c293d0839282c994ce6b8c671"}], "otherContent": [{"@id": "http://dl.cini.it/oa/items/26525/annolist.json", "@type": "sc:AnnotationList"}]}, {"@id": "http://dl.cini.it/oa/items/26526/canvas.json", "label": "p. 30, p. 31", "@type": "sc:Canvas", "width": 4162, "height": 3723, "images": [{"@id": "http://dl.cini.it/oa/files/26526/anno.json", "motivation": "sc:painting", "@type": "oa:Annotation", "resource": {"@id": "http://dl.cini.it/files/original/e397379feaeded905ce16b4a2c5436c0.jpg", "@type": "dctypes:Image", "format": "image/jpeg", "width": 4162, "height": 3723, "service": {"@id": "http://dl.cini.it:8080/digilib/Scaler/IIIF/e397379feaeded905ce16b4a2c5436c0.jpg", "@context": "http://iiif.io/api/image/2/context.json", "profile": "http://iiif.io/api/image/2/level2.json"}}, "on": "http://dl.cini.it/oa/items/26526/canvas.json"}], "metadata": [{"label": "Identifier", "value": "1477b273-9815-4788-aaac-44f4ce2ebd6d"}, {"label": "originalFileName", "value": "234887_ROL.0776.06.17.tif"}, {"label": "cartulazione1", "value": "p. 30, p. 31"}, {"label": "exifData", "value": "ColorSpace=-1;NativeDigest=36864,40960,40961,37121,37122,40962,40963,37510,40964,36867,36868,33434,33437,34850,34852,34855,34856,37377,37378,37379,37380,37381,37382,37383,37384,37385,37386,37396,41483,41484,41486,41487,41488,41492,41493,41495,41728,41729,41730,41985,41986,41987,41988,41989,41990,41991,41992,41993,41994,41995,41996,42016,0,2,4,5,6,7,8,9,10,11,12,13,14,15,16,17,18,20,22,23,24,25,26,27,28,30;D91764B97AECACA8A8386BB23B18ACD7;PixelXDimension=4162;PixelYDimension=3723"}, {"label": "filename", "value": "17.jpg"}, {"label": "fileMD5", "value": "cb374c2135fb8f6983e8bfb97659c6e3"}], "otherContent": [{"@id": "http://dl.cini.it/oa/items/26526/annolist.json", "@type": "sc:AnnotationList"}]}, {"@id": "http://dl.cini.it/oa/items/26527/canvas.json", "label": "p. 32, p. 33", "@type": "sc:Canvas", "width": 4162, "height": 3723, "images": [{"@id": "http://dl.cini.it/oa/files/26527/anno.json", "motivation": "sc:painting", "@type": "oa:Annotation", "resource": {"@id": "http://dl.cini.it/files/original/661d2a8f0d4b6c995f3e990e251e8393.jpg", "@type": "dctypes:Image", "format": "image/jpeg", "width": 4162, "height": 3723, "service": {"@id": "http://dl.cini.it:8080/digilib/Scaler/IIIF/661d2a8f0d4b6c995f3e990e251e8393.jpg", "@context": "http://iiif.io/api/image/2/context.json", "profile": "http://iiif.io/api/image/2/level2.json"}}, "on": "http://dl.cini.it/oa/items/26527/canvas.json"}], "metadata": [{"label": "Identifier", "value": "07f1f75e-43aa-445e-8ed5-dd6ea1b064a2"}, {"label": "originalFileName", "value": "234889_ROL.0776.06.18.tif"}, {"label": "cartulazione1", "value": "p. 32, p. 33"}, {"label": "exifData", "value": "ColorSpace=-1;NativeDigest=36864,40960,40961,37121,37122,40962,40963,37510,40964,36867,36868,33434,33437,34850,34852,34855,34856,37377,37378,37379,37380,37381,37382,37383,37384,37385,37386,37396,41483,41484,41486,41487,41488,41492,41493,41495,41728,41729,41730,41985,41986,41987,41988,41989,41990,41991,41992,41993,41994,41995,41996,42016,0,2,4,5,6,7,8,9,10,11,12,13,14,15,16,17,18,20,22,23,24,25,26,27,28,30;D91764B97AECACA8A8386BB23B18ACD7;PixelXDimension=4162;PixelYDimension=3723"}, {"label": "filename", "value": "18.jpg"}, {"label": "fileMD5", "value": "eff75ea9a2ac70a67e2471461fbfaf01"}], "otherContent": [{"@id": "http://dl.cini.it/oa/items/26527/annolist.json", "@type": "sc:AnnotationList"}]}, {"@id": "http://dl.cini.it/oa/items/26528/canvas.json", "label": "p. 34, p. 35", "@type": "sc:Canvas", "width": 4162, "height": 3723, "images": [{"@id": "http://dl.cini.it/oa/files/26528/anno.json", "motivation": "sc:painting", "@type": "oa:Annotation", "resource": {"@id": "http://dl.cini.it/files/original/1bd6ca2b66683525f2c8ebed7173eec5.jpg", "@type": "dctypes:Image", "format": "image/jpeg", "width": 4162, "height": 3723, "service": {"@id": "http://dl.cini.it:8080/digilib/Scaler/IIIF/1bd6ca2b66683525f2c8ebed7173eec5.jpg", "@context": "http://iiif.io/api/image/2/context.json", "profile": "http://iiif.io/api/image/2/level2.json"}}, "on": "http://dl.cini.it/oa/items/26528/canvas.json"}], "metadata": [{"label": "Identifier", "value": "e940f0b8-9c77-4f39-8463-04c61e019994"}, {"label": "originalFileName", "value": "234891_ROL.0776.06.19.tif"}, {"label": "cartulazione1", "value": "p. 34, p. 35"}, {"label": "exifData", "value": "ColorSpace=-1;NativeDigest=36864,40960,40961,37121,37122,40962,40963,37510,40964,36867,36868,33434,33437,34850,34852,34855,34856,37377,37378,37379,37380,37381,37382,37383,37384,37385,37386,37396,41483,41484,41486,41487,41488,41492,41493,41495,41728,41729,41730,41985,41986,41987,41988,41989,41990,41991,41992,41993,41994,41995,41996,42016,0,2,4,5,6,7,8,9,10,11,12,13,14,15,16,17,18,20,22,23,24,25,26,27,28,30;D91764B97AECACA8A8386BB23B18ACD7;PixelXDimension=4162;PixelYDimension=3723"}, {"label": "filename", "value": "19.jpg"}, {"label": "fileMD5", "value": "d471179804907010833e678b55936b4f"}], "otherContent": [{"@id": "http://dl.cini.it/oa/items/26528/annolist.json", "@type": "sc:AnnotationList"}]}, {"@id": "http://dl.cini.it/oa/items/26529/canvas.json", "label": "p. 36, p. 37", "@type": "sc:Canvas", "width": 4162, "height": 3723, "images": [{"@id": "http://dl.cini.it/oa/files/26529/anno.json", "motivation": "sc:painting", "@type": "oa:Annotation", "resource": {"@id": "http://dl.cini.it/files/original/96e0a6b52f9089b932e8d4b638dc3f86.jpg", "@type": "dctypes:Image", "format": "image/jpeg", "width": 4162, "height": 3723, "service": {"@id": "http://dl.cini.it:8080/digilib/Scaler/IIIF/96e0a6b52f9089b932e8d4b638dc3f86.jpg", "@context": "http://iiif.io/api/image/2/context.json", "profile": "http://iiif.io/api/image/2/level2.json"}}, "on": "http://dl.cini.it/oa/items/26529/canvas.json"}], "metadata": [{"label": "Identifier", "value": "573542c2-56f2-455c-bfee-71108b6a46cd"}, {"label": "originalFileName", "value": "234893_ROL.0776.06.20.tif"}, {"label": "cartulazione1", "value": "p. 36, p. 37"}, {"label": "exifData", "value": "ColorSpace=-1;NativeDigest=36864,40960,40961,37121,37122,40962,40963,37510,40964,36867,36868,33434,33437,34850,34852,34855,34856,37377,37378,37379,37380,37381,37382,37383,37384,37385,37386,37396,41483,41484,41486,41487,41488,41492,41493,41495,41728,41729,41730,41985,41986,41987,41988,41989,41990,41991,41992,41993,41994,41995,41996,42016,0,2,4,5,6,7,8,9,10,11,12,13,14,15,16,17,18,20,22,23,24,25,26,27,28,30;D91764B97AECACA8A8386BB23B18ACD7;PixelXDimension=4162;PixelYDimension=3723"}, {"label": "filename", "value": "20.jpg"}, {"label": "fileMD5", "value": "ca134faf1cc00977e0acaf460514bfcc"}], "otherContent": [{"@id": "http://dl.cini.it/oa/items/26529/annolist.json", "@type": "sc:AnnotationList"}]}, {"@id": "http://dl.cini.it/oa/items/26530/canvas.json", "label": "p. 38, p. 39", "@type": "sc:Canvas", "width": 4162, "height": 3723, "images": [{"@id": "http://dl.cini.it/oa/files/26530/anno.json", "motivation": "sc:painting", "@type": "oa:Annotation", "resource": {"@id": "http://dl.cini.it/files/original/a0f4ed8587da8a07931595e05855094f.jpg", "@type": "dctypes:Image", "format": "image/jpeg", "width": 4162, "height": 3723, "service": {"@id": "http://dl.cini.it:8080/digilib/Scaler/IIIF/a0f4ed8587da8a07931595e05855094f.jpg", "@context": "http://iiif.io/api/image/2/context.json", "profile": "http://iiif.io/api/image/2/level2.json"}}, "on": "http://dl.cini.it/oa/items/26530/canvas.json"}], "metadata": [{"label": "Identifier", "value": "3e4795c9-7376-40d2-8125-e60fde097233"}, {"label": "originalFileName", "value": "234895_ROL.0776.06.21.tif"}, {"label": "cartulazione1", "value": "p. 38, p. 39"}, {"label": "exifData", "value": "ColorSpace=-1;NativeDigest=36864,40960,40961,37121,37122,40962,40963,37510,40964,36867,36868,33434,33437,34850,34852,34855,34856,37377,37378,37379,37380,37381,37382,37383,37384,37385,37386,37396,41483,41484,41486,41487,41488,41492,41493,41495,41728,41729,41730,41985,41986,41987,41988,41989,41990,41991,41992,41993,41994,41995,41996,42016,0,2,4,5,6,7,8,9,10,11,12,13,14,15,16,17,18,20,22,23,24,25,26,27,28,30;D91764B97AECACA8A8386BB23B18ACD7;PixelXDimension=4162;PixelYDimension=3723"}, {"label": "filename", "value": "21.jpg"}, {"label": "fileMD5", "value": "4279cc434f653f9b7fd13ed8face6e62"}], "otherContent": [{"@id": "http://dl.cini.it/oa/items/26530/annolist.json", "@type": "sc:AnnotationList"}]}, {"@id": "http://dl.cini.it/oa/items/26531/canvas.json", "label": "p. 40, p. 41", "@type": "sc:Canvas", "width": 4152, "height": 3723, "images": [{"@id": "http://dl.cini.it/oa/files/26531/anno.json", "motivation": "sc:painting", "@type": "oa:Annotation", "resource": {"@id": "http://dl.cini.it/files/original/3a62e6d80ff0b7693fcc81495d41f8b2.jpg", "@type": "dctypes:Image", "format": "image/jpeg", "width": 4152, "height": 3723, "service": {"@id": "http://dl.cini.it:8080/digilib/Scaler/IIIF/3a62e6d80ff0b7693fcc81495d41f8b2.jpg", "@context": "http://iiif.io/api/image/2/context.json", "profile": "http://iiif.io/api/image/2/level2.json"}}, "on": "http://dl.cini.it/oa/items/26531/canvas.json"}], "metadata": [{"label": "Identifier", "value": "c0acbced-9aaa-4f0c-a928-2bf90e1f1232"}, {"label": "originalFileName", "value": "234897_ROL.0776.06.22.tif"}, {"label": "cartulazione1", "value": "p. 40, p. 41"}, {"label": "exifData", "value": "ColorSpace=-1;NativeDigest=36864,40960,40961,37121,37122,40962,40963,37510,40964,36867,36868,33434,33437,34850,34852,34855,34856,37377,37378,37379,37380,37381,37382,37383,37384,37385,37386,37396,41483,41484,41486,41487,41488,41492,41493,41495,41728,41729,41730,41985,41986,41987,41988,41989,41990,41991,41992,41993,41994,41995,41996,42016,0,2,4,5,6,7,8,9,10,11,12,13,14,15,16,17,18,20,22,23,24,25,26,27,28,30;853D799F9572868E5B98F867195DD545;PixelXDimension=4152;PixelYDimension=3723"}, {"label": "filename", "value": "22.jpg"}, {"label": "fileMD5", "value": "dd65d146f1f21af69c030a080002a80d"}], "otherContent": [{"@id": "http://dl.cini.it/oa/items/26531/annolist.json", "@type": "sc:AnnotationList"}]}, {"@id": "http://dl.cini.it/oa/items/26532/canvas.json", "label": "p. 42, p. 43", "@type": "sc:Canvas", "width": 4188, "height": 3723, "images": [{"@id": "http://dl.cini.it/oa/files/26532/anno.json", "motivation": "sc:painting", "@type": "oa:Annotation", "resource": {"@id": "http://dl.cini.it/files/original/f17cd5f6c1c8b2ed55de05c5ff2fb1ad.jpg", "@type": "dctypes:Image", "format": "image/jpeg", "width": 4188, "height": 3723, "service": {"@id": "http://dl.cini.it:8080/digilib/Scaler/IIIF/f17cd5f6c1c8b2ed55de05c5ff2fb1ad.jpg", "@context": "http://iiif.io/api/image/2/context.json", "profile": "http://iiif.io/api/image/2/level2.json"}}, "on": "http://dl.cini.it/oa/items/26532/canvas.json"}], "metadata": [{"label": "Identifier", "value": "2e8a0712-e4cb-4802-a1ef-1454e045d533"}, {"label": "originalFileName", "value": "234899_ROL.0776.06.23.tif"}, {"label": "cartulazione1", "value": "p. 42, p. 43"}, {"label": "exifData", "value": "ColorSpace=-1;NativeDigest=36864,40960,40961,37121,37122,40962,40963,37510,40964,36867,36868,33434,33437,34850,34852,34855,34856,37377,37378,37379,37380,37381,37382,37383,37384,37385,37386,37396,41483,41484,41486,41487,41488,41492,41493,41495,41728,41729,41730,41985,41986,41987,41988,41989,41990,41991,41992,41993,41994,41995,41996,42016,0,2,4,5,6,7,8,9,10,11,12,13,14,15,16,17,18,20,22,23,24,25,26,27,28,30;A4D13B3827C9F72C8B87F02658F3FB17;PixelXDimension=4188;PixelYDimension=3723"}, {"label": "filename", "value": "23.jpg"}, {"label": "fileMD5", "value": "93c36ac1cd66fdc742979e585b103cf9"}], "otherContent": [{"@id": "http://dl.cini.it/oa/items/26532/annolist.json", "@type": "sc:AnnotationList"}]}, {"@id": "http://dl.cini.it/oa/items/26533/canvas.json", "label": "p. 44, p. 45", "@type": "sc:Canvas", "width": 4188, "height": 3723, "images": [{"@id": "http://dl.cini.it/oa/files/26533/anno.json", "motivation": "sc:painting", "@type": "oa:Annotation", "resource": {"@id": "http://dl.cini.it/files/original/b428aab5a2cdf8e3d984422f77cd0a28.jpg", "@type": "dctypes:Image", "format": "image/jpeg", "width": 4188, "height": 3723, "service": {"@id": "http://dl.cini.it:8080/digilib/Scaler/IIIF/b428aab5a2cdf8e3d984422f77cd0a28.jpg", "@context": "http://iiif.io/api/image/2/context.json", "profile": "http://iiif.io/api/image/2/level2.json"}}, "on": "http://dl.cini.it/oa/items/26533/canvas.json"}], "metadata": [{"label": "Identifier", "value": "5f7ad804-9cf6-4d66-ac89-9a0a310ab044"}, {"label": "originalFileName", "value": "234901_ROL.0776.06.24.tif"}, {"label": "cartulazione1", "value": "p. 44, p. 45"}, {"label": "exifData", "value": "ColorSpace=-1;NativeDigest=36864,40960,40961,37121,37122,40962,40963,37510,40964,36867,36868,33434,33437,34850,34852,34855,34856,37377,37378,37379,37380,37381,37382,37383,37384,37385,37386,37396,41483,41484,41486,41487,41488,41492,41493,41495,41728,41729,41730,41985,41986,41987,41988,41989,41990,41991,41992,41993,41994,41995,41996,42016,0,2,4,5,6,7,8,9,10,11,12,13,14,15,16,17,18,20,22,23,24,25,26,27,28,30;A4D13B3827C9F72C8B87F02658F3FB17;PixelXDimension=4188;PixelYDimension=3723"}, {"label": "filename", "value": "24.jpg"}, {"label": "fileMD5", "value": "a7d12679ba1cce293af3f71dd14c4a1e"}], "otherContent": [{"@id": "http://dl.cini.it/oa/items/26533/annolist.json", "@type": "sc:AnnotationList"}]}, {"@id": "http://dl.cini.it/oa/items/26534/canvas.json", "label": "p. 46, p. [47]", "@type": "sc:Canvas", "width": 4162, "height": 3723, "images": [{"@id": "http://dl.cini.it/oa/files/26534/anno.json", "motivation": "sc:painting", "@type": "oa:Annotation", "resource": {"@id": "http://dl.cini.it/files/original/23af8102915533061ceb56651da0812e.jpg", "@type": "dctypes:Image", "format": "image/jpeg", "width": 4162, "height": 3723, "service": {"@id": "http://dl.cini.it:8080/digilib/Scaler/IIIF/23af8102915533061ceb56651da0812e.jpg", "@context": "http://iiif.io/api/image/2/context.json", "profile": "http://iiif.io/api/image/2/level2.json"}}, "on": "http://dl.cini.it/oa/items/26534/canvas.json"}], "metadata": [{"label": "Identifier", "value": "32407a53-f450-4a83-9d8b-b41faf53fc9a"}, {"label": "originalFileName", "value": "234903_ROL.0776.06.25.tif"}, {"label": "cartulazione1", "value": "p. 46, p. [47]"}, {"label": "exifData", "value": "ColorSpace=-1;NativeDigest=36864,40960,40961,37121,37122,40962,40963,37510,40964,36867,36868,33434,33437,34850,34852,34855,34856,37377,37378,37379,37380,37381,37382,37383,37384,37385,37386,37396,41483,41484,41486,41487,41488,41492,41493,41495,41728,41729,41730,41985,41986,41987,41988,41989,41990,41991,41992,41993,41994,41995,41996,42016,0,2,4,5,6,7,8,9,10,11,12,13,14,15,16,17,18,20,22,23,24,25,26,27,28,30;D91764B97AECACA8A8386BB23B18ACD7;PixelXDimension=4162;PixelYDimension=3723"}, {"label": "filename", "value": "25.jpg"}, {"label": "fileMD5", "value": "990ffeccb51427b8c57c279ddcccd2f5"}], "otherContent": [{"@id": "http://dl.cini.it/oa/items/26534/annolist.json", "@type": "sc:AnnotationList"}]}, {"@id": "http://dl.cini.it/oa/items/26535/canvas.json", "label": "p. [48], coperta_3", "@type": "sc:Canvas", "width": 4162, "height": 3732, "images": [{"@id": "http://dl.cini.it/oa/files/26535/anno.json", "motivation": "sc:painting", "@type": "oa:Annotation", "resource": {"@id": "http://dl.cini.it/files/original/3927a42b8cf38d41f13b9c16908e0886.jpg", "@type": "dctypes:Image", "format": "image/jpeg", "width": 4162, "height": 3732, "service": {"@id": "http://dl.cini.it:8080/digilib/Scaler/IIIF/3927a42b8cf38d41f13b9c16908e0886.jpg", "@context": "http://iiif.io/api/image/2/context.json", "profile": "http://iiif.io/api/image/2/level2.json"}}, "on": "http://dl.cini.it/oa/items/26535/canvas.json"}], "metadata": [{"label": "Identifier", "value": "f4758537-9f00-463a-90a7-bfeb6ee78814"}, {"label": "originalFileName", "value": "234905_ROL.0776.06.26.tif"}, {"label": "cartulazione1", "value": "p. [48], coperta_3"}, {"label": "exifData", "value": "ColorSpace=-1;NativeDigest=36864,40960,40961,37121,37122,40962,40963,37510,40964,36867,36868,33434,33437,34850,34852,34855,34856,37377,37378,37379,37380,37381,37382,37383,37384,37385,37386,37396,41483,41484,41486,41487,41488,41492,41493,41495,41728,41729,41730,41985,41986,41987,41988,41989,41990,41991,41992,41993,41994,41995,41996,42016,0,2,4,5,6,7,8,9,10,11,12,13,14,15,16,17,18,20,22,23,24,25,26,27,28,30;735E74363DDF2122C7E72F18E4FF23E8;PixelXDimension=4162;PixelYDimension=3732"}, {"label": "filename", "value": "26.jpg"}, {"label": "fileMD5", "value": "15763decf61c056ee474e62bbcc1821b"}], "otherContent": [{"@id": "http://dl.cini.it/oa/items/26535/annolist.json", "@type": "sc:AnnotationList"}]}, {"@id": "http://dl.cini.it/oa/items/26536/canvas.json", "label": "coperta_4", "@type": "sc:Canvas", "width": 3830, "height": 4981, "images": [{"@id": "http://dl.cini.it/oa/files/26536/anno.json", "motivation": "sc:painting", "@type": "oa:Annotation", "resource": {"@id": "http://dl.cini.it/files/original/c87ab2c7b5e775c69ea9a9f00c8f357a.jpg", "@type": "dctypes:Image", "format": "image/jpeg", "width": 3830, "height": 4981, "service": {"@id": "http://dl.cini.it:8080/digilib/Scaler/IIIF/c87ab2c7b5e775c69ea9a9f00c8f357a.jpg", "@context": "http://iiif.io/api/image/2/context.json", "profile": "http://iiif.io/api/image/2/level2.json"}}, "on": "http://dl.cini.it/oa/items/26536/canvas.json"}], "metadata": [{"label": "Identifier", "value": "1dc4b191-d39a-435e-9cef-bc110bc9f01e"}, {"label": "originalFileName", "value": "234907_ROL.0776.06.27.tif"}, {"label": "cartulazione1", "value": "coperta_4"}, {"label": "exifData", "value": "ColorSpace=-1;NativeDigest=36864,40960,40961,37121,37122,40962,40963,37510,40964,36867,36868,33434,33437,34850,34852,34855,34856,37377,37378,37379,37380,37381,37382,37383,37384,37385,37386,37396,41483,41484,41486,41487,41488,41492,41493,41495,41728,41729,41730,41985,41986,41987,41988,41989,41990,41991,41992,41993,41994,41995,41996,42016,0,2,4,5,6,7,8,9,10,11,12,13,14,15,16,17,18,20,22,23,24,25,26,27,28,30;39AAF879E7BDCA73148901029947363E;PixelXDimension=3830;PixelYDimension=4981"}, {"label": "filename", "value": "27.jpg"}, {"label": "fileMD5", "value": "72d351aa18f6a3dc8d2145e04f945827"}], "otherContent": [{"@id": "http://dl.cini.it/oa/items/26536/annolist.json", "@type": "sc:AnnotationList"}]}]}], "metadata": [{"label": "Identifier", "value": "a944754f-76fc-4ed9-acfe-32a004353f21"}, {"label": "maintenanceagency", "value": "Fondazione Giorgio Cini"}, {"label": "recordid", "value": "MUS0005578"}, {"label": "series", "value": "Fondo Ulderico Rolandi"}, {"label": "title", "value": "L' infedelta' delusa dramma pastorale da rappresentarsi in musica nel Teatro delle Grazie in Vicenza in occasione della Fiera di maggio dell'anno 1729. Consagrato a S.S. E.E. il n.h. f. Antonio Diedo podesta', e vice capitanio, et la n.d. Andreana Michiel Diedo sua degnissima consorte"}, {"label": "level", "value": "Unit\u00e0 documentaria"}, {"label": "type", "value": "Testo a stampa"}, {"label": "creator", "value": "Cassani, Francesco<fl. 1729; librettista>"}, {"label": "date_year_start", "value": "1729"}], "service": [{"@context": "http://iiif.io/api/search/1/context.json", "@id": "http://dl.cini.it/oa/collections/830/search", "label": "Search this manifest", "profile": "http://iiif.io/api/search/1/search"}]}